rmfuse/__init__.py
rmfuse/config.py
rmfuse/fuse.py
rmfuse/fuselib.py
rmfuse/list.py
rmfuse-0.2.3.dist-info/entry_points.txt
rmfuse-0.2.3.dist-info/LICENSE.txt
rmfuse-0.2.3.dist-info/WHEEL
rmfuse-0.2.3.dist-info/METADATA
rmfuse-0.2.3.dist-info/RECORD
