Metadata-Version: 2.1
Name: rmfuse
Version: 0.2.3
Summary: 
Home-page: https://github.com/rschroll/rmfuse
License: MIT
Author: Robert Schroll
Author-email: rschroll@gmail.com
Requires-Python: >=3.7,<4.0
Classifier: License :: OSI Approved :: MIT License
Classifier: Programming Language :: Python :: 3
Classifier: Programming Language :: Python :: 3.7
Classifier: Programming Language :: Python :: 3.8
Classifier: Programming Language :: Python :: 3.9
Provides-Extra: llfuse
Provides-Extra: pyfuse3
Requires-Dist: bidict (>=0.21.2,<0.22.0)
Requires-Dist: llfuse (>=1.4.1,<2.0.0); extra == "llfuse"
Requires-Dist: pyfuse3 (>=3.2.0,<4.0.0); extra == "pyfuse3"
Requires-Dist: rmcl (>=0.4.2,<0.5.0)
Requires-Dist: rmrl (>=0.2.1,<0.3.0)
Requires-Dist: xdg (>=5.0.1,<6.0.0)
Project-URL: Repository, https://github.com/rschroll/rmfuse
